{
  "FilterHeaders": [
    {
      "Header": "x-http-method-override",
      "IncludeInScript": false
    },
    {
      "Header": "x-goog-update-updater",
      "IncludeInScript": false
    },
    {
      "Header": "x-goog-update-interactivity",
      "IncludeInScript": false
    },
    {
      "Header": "x-goog-update-appid",
      "IncludeInScript": false
    },
    {
      "Header": "x-goog-encode-response-if-executable",
      "IncludeInScript": false
    },
    {
      "Header": "x-goog-api-key",
      "IncludeInScript": false
    },
    {
      "Header": "x-client-data",
      "IncludeInScript": false
    },
    {
      "Header": "user-agent",
      "IncludeInScript": false
    },
    {
      "Header": "upgrade-insecure-requests",
      "IncludeInScript": false
    },
    {
      "Header": "sec-fetch-user",
      "IncludeInScript": false
    },
    {
      "Header": "sec-fetch-site",
      "IncludeInScript": false
    },
    {
      "Header": "sec-fetch-mode",
      "IncludeInScript": false
    },
    {
      "Header": "sec-fetch-dest",
      "IncludeInScript": false
    },
    {
      "Header": "sec-ch-ua-platform",
      "IncludeInScript": false
    },
    {
      "Header": "sec-ch-ua-mobile",
      "IncludeInScript": false
    },
    {
      "Header": "sec-ch-ua",
      "IncludeInScript": false
    },
    {
      "Header": "pragma",
      "IncludeInScript": false
    },
    {
      "Header": "origin",
      "IncludeInScript": false
    },
    {
      "Header": "if-none-match",
      "IncludeInScript": false
    },
    {
      "Header": "content-encoding",
      "IncludeInScript": false
    },
    {
      "Header": "cache-control",
      "IncludeInScript": false
    },
    {
      "Header": "authorization",
      "IncludeInScript": false
    },
    {
      "Header": "access-control-request-method",
      "IncludeInScript": false
    },
    {
      "Header": "access-control-request-headers",
      "IncludeInScript": false
    },
    {
      "Header": "accept-language",
      "IncludeInScript": false
    },
    {
      "Header": "accept-encoding",
      "IncludeInScript": false
    },
    {
      "Header": "accept",
      "IncludeInScript": false
    },
    {
      "Header": "a-im",
      "IncludeInScript": false
    }
  ],
  "FilterResources": [
    {
      "IsNonResource": false,
      "type": "text/plain"
    },
    {
      "IsNonResource": true,
      "type": "text/html"
    },
    {
      "IsNonResource": false,
      "type": "text/css"
    },
    {
      "IsNonResource": false,
      "type": "image/jpeg"
    },
    {
      "IsNonResource": false,
      "type": "application/x-protobuf"
    },
    {
      "IsNonResource": false,
      "type": "application/vnd.google.octet-stream-compressible"
    },
    {
      "IsNonResource": true,
      "type": "application/json"
    },
    {
      "IsNonResource": false,
      "type": "application/javascript"
    }
  ],
  "GeneralInfo": {
    "BrowserVersion": "",
    "IsWinInetMode": false,
    "MaxUsedConnections": 11,
    "RecordedBrowser": "Chrome",
    "RecordingDate": "Feb-06-2024",
    "RecordingDuration": 252203,
    "RecordingMode": "N/A",
    "RecordingTimeStamp": 1707230224,
    "RecordingType": "Browser",
    "TotalBytesReceived": 417439,
    "TotalBytesSent": 23950,
    "TotalRequests": 19,
    "UserAgent": "Mozilla/5.0 (Windows NT 10.0; Win64; x64) AppleWebKit/537.36 (KHTML, like Gecko) Chrome/121.0.0.0 Safari/537.36"
  },
  "HostInfo": [
    {
      "DomainName": "herokuapp.com",
      "Domains": [
        {
          "HTTPVersion": "HTTP/1.1",
          "IP": "54.235.77.118",
          "IncludeInScript": true,
          "Name": "katalon-demo-cura.herokuapp.com",
          "Port": 443,
          "Requests": [
            {
              "CompressionType": "",
              "DataType": "text/html",
              "DownloadTime": 234,
              "EventId": 472,
              "HttpStatus": 200,
              "Size": 4234,
              "URL": "https://katalon-demo-cura.herokuapp.com/"
            },
            {
              "CompressionType": "",
              "DataType": "text/html",
              "DownloadTime": 235,
              "EventId": 470,
              "HttpStatus": 302,
              "Size": 0,
              "URL": "https://katalon-demo-cura.herokuapp.com/authenticate.php?logout"
            },
            {
              "CompressionType": "",
              "DataType": "text/html",
              "DownloadTime": 234,
              "EventId": 464,
              "HttpStatus": 200,
              "Size": 6656,
              "URL": "https://katalon-demo-cura.herokuapp.com/appointment.php"
            },
            {
              "CompressionType": "",
              "DataType": "text/html",
              "DownloadTime": 234,
              "EventId": 453,
              "HttpStatus": 200,
              "Size": 8280,
              "URL": "https://katalon-demo-cura.herokuapp.com/"
            },
            {
              "CompressionType": "",
              "DataType": "text/html",
              "DownloadTime": 250,
              "EventId": 451,
              "HttpStatus": 302,
              "Size": 0,
              "URL": "https://katalon-demo-cura.herokuapp.com/authenticate.php"
            },
            {
              "CompressionType": "",
              "DataType": "text/html",
              "DownloadTime": 234,
              "EventId": 410,
              "HttpStatus": 200,
              "Size": 7261,
              "URL": "https://katalon-demo-cura.herokuapp.com/profile.php"
            },
            {
              "CompressionType": "",
              "DataType": "text/html",
              "DownloadTime": 234,
              "EventId": 362,
              "HttpStatus": 404,
              "Size": 196,
              "URL": "https://katalon-demo-cura.herokuapp.com/favicon.ico"
            },
            {
              "CompressionType": "",
              "DataType": "image/jpeg",
              "DownloadTime": 234,
              "EventId": 315,
              "HttpStatus": 200,
              "Size": 379361,
              "URL": "https://katalon-demo-cura.herokuapp.com//img/header.jpg"
            },
            {
              "CompressionType": "",
              "DataType": "application/javascript",
              "DownloadTime": 235,
              "EventId": 299,
              "HttpStatus": 200,
              "Size": 1589,
              "URL": "https://katalon-demo-cura.herokuapp.com//js/theme.js"
            },
            {
              "CompressionType": "",
              "DataType": "text/css",
              "DownloadTime": 235,
              "EventId": 282,
              "HttpStatus": 200,
              "Size": 3211,
              "URL": "https://katalon-demo-cura.herokuapp.com//css/theme.css"
            },
            {
              "CompressionType": "",
              "DataType": "text/html",
              "DownloadTime": 235,
              "EventId": 278,
              "HttpStatus": 200,
              "Size": 4234,
              "URL": "https://katalon-demo-cura.herokuapp.com/"
            }
          ],
          "SSLCipher": "",
          "SSLVersion": ""
        }
      ],
      "IncludeInScript": true
    },
    {
      "DomainName": "heroku.com",
      "Domains": [
        {
          "HTTPVersion": "HTTP/1.1",
          "IP": "34.242.127.23",
          "IncludeInScript": true,
          "Name": "nel.heroku.com",
          "Port": 443,
          "Requests": [
            {
              "CompressionType": "",
              "DataType": "text/plain",
              "DownloadTime": 156,
              "EventId": 436,
              "HttpStatus": 204,
              "Size": 0,
              "URL": "https://nel.heroku.com/reports?ts=1707204062&sid=67ff5de4-ad2b-4112-9289-cf96be89efed&s=3gWfdqgqag20ISrvqJ8fxyJ0Y1%2BF3suXBjpImS7Xw5Y%3D"
            },
            {
              "CompressionType": "",
              "DataType": "",
              "DownloadTime": 156,
              "EventId": 434,
              "HttpStatus": 200,
              "Size": 0,
              "URL": "https://nel.heroku.com/reports?ts=1707204062&sid=67ff5de4-ad2b-4112-9289-cf96be89efed&s=3gWfdqgqag20ISrvqJ8fxyJ0Y1%2BF3suXBjpImS7Xw5Y%3D"
            },
            {
              "CompressionType": "",
              "DataType": "",
              "DownloadTime": 297,
              "EventId": 384,
              "HttpStatus": 200,
              "Size": 0,
              "URL": "https://nel.heroku.com/reports?ts=1707204039&sid=67ff5de4-ad2b-4112-9289-cf96be89efed&s=cmMX5FsbMuzj%2FMvUiBbgjzqcdPotdNhjjJZsXIQ9h8M%3D"
            }
          ],
          "SSLCipher": "TLS_AES_128_GCM_SHA256",
          "SSLVersion": "TLS1.3"
        }
      ],
      "IncludeInScript": true
    },
    {
      "DomainName": "googleapis.com",
      "Domains": [
        {
          "HTTPVersion": "HTTP/1.1",
          "IP": "142.250.76.35",
          "IncludeInScript": true,
          "Name": "update.googleapis.com",
          "Port": 443,
          "Requests": [
            {
              "CompressionType": "gzip",
              "DataType": "application/json",
              "DownloadTime": 281,
              "EventId": 426,
              "HttpStatus": 200,
              "Size": 904,
              "URL": "https://update.googleapis.com/service/update2/json?cup2key=13:8DEg-pzeuBd4oawTjgr-4x0EcXAm5IsA00LPDaBzufk&cup2hreq=02b619b30f0611e2d3d93cef06615eb665467506221e5dd83fd7cce05d9169f0"
            }
          ],
          "SSLCipher": "TLS_AES_256_GCM_SHA384",
          "SSLVersion": "TLS1.3"
        },
        {
          "HTTPVersion": "HTTP/1.1",
          "IP": "142.250.195.202",
          "IncludeInScript": true,
          "Name": "safebrowsing.googleapis.com",
          "Port": 443,
          "Requests": [
            {
              "CompressionType": "",
              "DataType": "application/x-protobuf",
              "DownloadTime": 31,
              "EventId": 442,
              "HttpStatus": 200,
              "Size": 1135,
              "URL": "https://safebrowsing.googleapis.com/v4/threatListUpdates:fetch?$req=Ch4KDGdvb2dsZWNocm9tZRIOMTIxLjAuNjE2Ny4xNDAaKQgFEAEaGwoNCAUQBhgBIgMwMDEwARCQlRUaAhgLJqhWkyIEIAEgAigBGikIARABGhsKDQgBEAYYASIDMDAxMAEQs-kNGgIYC0gH-lQiBCABIAIoARopCAMQARobCg0IAxAGGAEiAzAwMTABEOvgDRoCGAuISvtoIgQgASACKAEaKQgOEAEaGwoNCA4QBhgBIgMwMDEwARC0rwcaAhgL_VjDViIEIAEgAigBGigIARAIGhoKDQgBEAgYASIDMDAxMAQQ3DcaAhgLwLZjkiIEIAEgAigEGikIDxABGhsKDQgPEAYYASIDMDAxMAEQ86sCGgIYC_ai3uMiBCABIAIoARonCAoQCBoZCg0IChAIGAEiAzAwMTABEAcaAhgLYjna-CIEIAEgAigBGicICRABGhkKDQgJEAYYASIDMDAxMAEQIxoCGAuXnkjLIgQgASACKAEaKAgIEAEaGgoNCAgQBhgBIgMwMDEwARCwFRoCGAteoQ6BIgQgASACKAEaKQgNEAEaGwoNCA0QBhgBIgMwMDEwARCGjQIaAhgLVXGC1iIEIAEgAigBGikIBxABGhsKDQgHEAYYASIDMDAxMAEQ6q8OGgIYC8xMQtoiBCABIAIoARooCBAQARoaCg0IEBAGGAEiAzAwMTABEIshGgIYC7kwzGAiBCABIAIoASICCAE=&$ct=application/x-protobuf&key=AIzaSyBOti4mM-6x9WDnZIjIeyEU21OpBXqWBgw"
            }
          ],
          "SSLCipher": "TLS_AES_256_GCM_SHA384",
          "SSLVersion": "TLS1.3"
        },
        {
          "HTTPVersion": "HTTP/1.1",
          "IP": "142.250.182.42",
          "IncludeInScript": true,
          "Name": "content-autofill.googleapis.com",
          "Port": 443,
          "Requests": [
            {
              "CompressionType": "gzip",
              "DataType": "text/plain",
              "DownloadTime": 109,
              "EventId": 420,
              "HttpStatus": 200,
              "Size": 63,
              "URL": "https://content-autofill.googleapis.com/v1/pages/ChVDaHJvbWUvMTIxLjAuNjE2Ny4xNDASLgkHqZJskw0sFxIFDZFhlU4SBQ2RYZVOEgUN541ADhIFDc5BTHohwfHPmPIHasw=?alt=proto"
            }
          ],
          "SSLCipher": "TLS_AES_256_GCM_SHA384",
          "SSLVersion": "TLS1.3"
        },
        {
          "HTTPVersion": "HTTP/1.1",
          "IP": "142.250.195.99",
          "IncludeInScript": true,
          "Name": "clientservices.googleapis.com",
          "Port": 443,
          "Requests": [
            {
              "CompressionType": "",
              "DataType": "",
              "DownloadTime": 218,
              "EventId": 276,
              "HttpStatus": 304,
              "Size": 0,
              "URL": "https://clientservices.googleapis.com/chrome-variations/seed?osname=win&channel=stable&milestone=121"
            }
          ],
          "SSLCipher": "TLS_AES_256_GCM_SHA384",
          "SSLVersion": "TLS1.3"
        }
      ],
      "IncludeInScript": true
    },
    {
      "DomainName": "google.com",
      "Domains": [
        {
          "HTTPVersion": "HTTP/1.1",
          "IP": "142.250.205.238",
          "IncludeInScript": true,
          "Name": "clients4.google.com",
          "Port": 443,
          "Requests": [
            {
              "CompressionType": "gzip",
              "DataType": "application/vnd.google.octet-stream-compressible",
              "DownloadTime": 578,
              "EventId": 402,
              "HttpStatus": 200,
              "Size": 315,
              "URL": "https://clients4.google.com/chrome-sync/command/?client=Google+Chrome&client_id=EqBJmtXuwdBaPOmd8C%2FKQg%3D%3D"
            }
          ],
          "SSLCipher": "TLS_AES_256_GCM_SHA384",
          "SSLVersion": "TLS1.3"
        }
      ],
      "IncludeInScript": true
    }
  ],
  "WebSocket": {
    "IncludeInScript": false,
    "IsScriptIncludeWebSocket": false
  },
  "NumberOfCorrelations": 6
}